tpyconfig/__init__.py
tpyconfig/tpyconfig.py
pyrotash-0.2.dist-info/METADATA
pyrotash-0.2.dist-info/WHEEL
pyrotash-0.2.dist-info/top_level.txt
pyrotash-0.2.dist-info/RECORD
