Metadata-Version: 2.1
Name: pyrotash
Version: 0.2
Summary: A simple package for managing configuration variables.
Author: Tashri
Author-email: Tashrithakur2342@gmail.com
Classifier: Programming Language :: Python :: 3
Classifier: License :: OSI Approved :: MIT License
Classifier: Operating System :: OS Independent
